README
setup.cfg
setup.py
lava/__init__.py
lava/serial/__init__.py
lava/serial/commands.py
lava/serial/console.py
lava/serial/direct.py
lava/serial/miniterm.py
lava/serial/rfc2217_server.py
lava_serial.egg-info/PKG-INFO
lava_serial.egg-info/SOURCES.txt
lava_serial.egg-info/dependency_links.txt
lava_serial.egg-info/entry_points.txt
lava_serial.egg-info/namespace_packages.txt
lava_serial.egg-info/requires.txt
lava_serial.egg-info/top_level.txt
lava_serial.egg-info/zip-safe